{
  "id": "1155060",
  "kanji": "以下",
  "readings": [
    "いか"
  ],
  "meanings": [
    "not exceeding ...",
    "not more than ...",
    "... and under",
    "... and below",
    "... or fewer",
    "below (a standard, level, etc.)",
    "under",
    "beneath",
    "less than",
    "the following",
    "the below-mentioned",
    "the rest",
    "followed by ...",
    "including ...",
    "... and other (employees, officials, etc.)"
  ],
  "frequency": 2468,
  "containedKanji": [
    "以",
    "下"
  ],
  "pos": [
    "n-suf",
    "n-suf",
    "n",
    "adj-no",
    "n-suf"
  ]
}