{
  "id": "1158880",
  "writtenForm": {
    "kanji": "違う",
    "containedKanji": [
      "違"
    ]
  },
  "reading": {
    "primary": "ちがう",
    "alternatives": []
  },
  "frequency": {
    "kanjiRank": 131,
    "kanaRank": 3489
  },
  "progression": {
    "kklcStep": 663
  },
  "senses": [
    {
      "pos": [
        "v5u",
        "vi"
      ],
      "misc": {
        "isAbbreviation": false,
        "isSuffix": false,
        "isPrefix": false,
        "isArchaic": false,
        "isRare": false,
        "rawTags": []
      },
      "glosses": [
        "to differ (from)",
        "to be different",
        "to be distinct",
        "to be unlike",
        "to vary",
        "to disagree (with)"
      ],
      "related": {
        "compounds": []
      }
    },
    {
      "pos": [
        "v5u",
        "vi"
      ],
      "misc": {
        "isAbbreviation": false,
        "isSuffix": false,
        "isPrefix": false,
        "isArchaic": false,
        "isRare": false,
        "rawTags": []
      },
      "glosses": [
        "to be wrong",
        "to be incorrect",
        "to be mistaken"
      ],
      "related": {
        "compounds": []
      }
    },
    {
      "pos": [
        "v5u",
        "vi"
      ],
      "misc": {
        "isAbbreviation": false,
        "isSuffix": false,
        "isPrefix": false,
        "isArchaic": false,
        "isRare": false,
        "rawTags": []
      },
      "glosses": [
        "to become abnormal",
        "to go wrong"
      ],
      "related": {
        "compounds": [
          "気が違う"
        ]
      }
    },
    {
      "pos": [
        "exp"
      ],
      "misc": {
        "isAbbreviation": false,
        "isSuffix": false,
        "isPrefix": false,
        "isArchaic": false,
        "isRare": false,
        "rawTags": []
      },
      "glosses": [
        "isn't it?",
        "wasn't it?"
      ],
      "related": {
        "compounds": []
      }
    }
  ],
  "usageHints": {
    "requiresContext": false
  }
}