{
  "id": "1158450",
  "writtenForm": {
    "kanji": "維持",
    "containedKanji": [
      "維",
      "持"
    ]
  },
  "reading": {
    "primary": "いじ",
    "alternatives": []
  },
  "frequency": {
    "kanjiRank": 2575,
    "kanaRank": 143641
  },
  "progression": {
    "kklcStep": 2149
  },
  "senses": [
    {
      "pos": [
        "n",
        "vs",
        "vt"
      ],
      "misc": {
        "isAbbreviation": false,
        "isSuffix": false,
        "isPrefix": false,
        "isArchaic": false,
        "isRare": false,
        "rawTags": []
      },
      "glosses": [
        "maintenance",
        "preservation",
        "improvement"
      ],
      "related": {
        "compounds": []
      }
    }
  ],
  "usageHints": {
    "requiresContext": false
  }
}