{
  "id": "1163400",
  "writtenForm": {
    "kanji": "一緒",
    "containedKanji": [
      "一",
      "緒"
    ]
  },
  "reading": {
    "primary": "いっしょ",
    "alternatives": []
  },
  "frequency": {
    "kanjiRank": 885,
    "kanaRank": 9481
  },
  "progression": {
    "kklcStep": 1450
  },
  "senses": [
    {
      "pos": [
        "n"
      ],
      "misc": {
        "isAbbreviation": false,
        "isSuffix": false,
        "isPrefix": false,
        "isArchaic": false,
        "isRare": false,
        "rawTags": []
      },
      "glosses": [
        "(doing) together"
      ],
      "related": {
        "compounds": []
      }
    },
    {
      "pos": [
        "n"
      ],
      "misc": {
        "isAbbreviation": false,
        "isSuffix": false,
        "isPrefix": false,
        "isArchaic": false,
        "isRare": false,
        "rawTags": []
      },
      "glosses": [
        "one lump",
        "one mixture",
        "the same category"
      ],
      "related": {
        "compounds": []
      }
    },
    {
      "pos": [
        "adj-no",
        "n"
      ],
      "misc": {
        "isAbbreviation": false,
        "isSuffix": false,
        "isPrefix": false,
        "isArchaic": false,
        "isRare": false,
        "rawTags": []
      },
      "glosses": [
        "the same",
        "identical"
      ],
      "related": {
        "compounds": []
      }
    },
    {
      "pos": [
        "n"
      ],
      "misc": {
        "isAbbreviation": false,
        "isSuffix": false,
        "isPrefix": false,
        "isArchaic": false,
        "isRare": false,
        "rawTags": []
      },
      "glosses": [
        "(at) the same time"
      ],
      "related": {
        "compounds": []
      }
    }
  ],
  "usageHints": {
    "requiresContext": false
  }
}