{
  "id": "1164740",
  "writtenForm": {
    "kanji": "一致",
    "containedKanji": [
      "一",
      "致"
    ]
  },
  "reading": {
    "primary": "いっち",
    "alternatives": []
  },
  "frequency": {
    "kanjiRank": 2908,
    "kanaRank": 13969
  },
  "progression": {
    "kklcStep": 251
  },
  "senses": [
    {
      "pos": [
        "n",
        "vs",
        "vi"
      ],
      "misc": {
        "isAbbreviation": false,
        "isSuffix": false,
        "isPrefix": false,
        "isArchaic": false,
        "isRare": false,
        "rawTags": []
      },
      "glosses": [
        "agreement",
        "accord",
        "correspondence",
        "consistency",
        "coincidence",
        "match"
      ],
      "related": {
        "compounds": []
      }
    },
    {
      "pos": [
        "n",
        "vs",
        "vi"
      ],
      "misc": {
        "isAbbreviation": false,
        "isSuffix": false,
        "isPrefix": false,
        "isArchaic": false,
        "isRare": false,
        "rawTags": []
      },
      "glosses": [
        "union",
        "unity",
        "cooperation"
      ],
      "related": {
        "compounds": []
      }
    }
  ],
  "usageHints": {
    "requiresContext": false
  }
}