{
  "id": "1208870",
  "kanji": "叶う",
  "readings": [
    "かなう"
  ],
  "meanings": [
    "to come true (of a dream, wish, etc.)",
    "to be realized",
    "to be fulfilled",
    "to be granted",
    "to be answered (of a prayer)",
    "to be requited (of love)",
    "to suit (one's needs, tastes, purpose, etc.)",
    "to serve",
    "to meet (one's expectations, wishes, etc.)",
    "to measure up to (e.g. one's ideal)",
    "to conform to (the law, standards, etc.)",
    "to be consistent with (reason, morality, etc.)",
    "to match",
    "to be a match for",
    "to rival",
    "to equal",
    "to compare with"
  ],
  "frequency": 2718,
  "hiraganaFrequency": 3424,
  "containedKanji": [
    "叶"
  ],
  "pos": [
    "v5u",
    "vi",
    "v5u",
    "vi",
    "v5u",
    "vi"
  ]
}