{
  "id": "1245470",
  "writtenForm": {
    "kanji": "空気",
    "containedKanji": [
      "空",
      "気"
    ]
  },
  "reading": {
    "primary": "くうき",
    "alternatives": []
  },
  "frequency": {
    "kanjiRank": 669,
    "kanaRank": 89356
  },
  "progression": {
    "kklcStep": 398
  },
  "senses": [
    {
      "pos": [
        "n"
      ],
      "misc": {
        "isAbbreviation": false,
        "isSuffix": false,
        "isPrefix": false,
        "isArchaic": false,
        "isRare": false,
        "rawTags": []
      },
      "glosses": [
        "air",
        "atmosphere"
      ],
      "related": {
        "compounds": []
      }
    },
    {
      "pos": [
        "n"
      ],
      "misc": {
        "isAbbreviation": false,
        "isSuffix": false,
        "isPrefix": false,
        "isArchaic": false,
        "isRare": false,
        "rawTags": []
      },
      "glosses": [
        "mood",
        "situation"
      ],
      "related": {
        "compounds": [
          "空気を読む"
        ]
      }
    },
    {
      "pos": [
        "n"
      ],
      "misc": {
        "isAbbreviation": false,
        "isSuffix": false,
        "isPrefix": false,
        "isArchaic": false,
        "isRare": false,
        "rawTags": [
          "col",
          "id"
        ]
      },
      "glosses": [
        "someone with no presence",
        "someone who doesn't stand out at all"
      ],
      "related": {
        "compounds": []
      }
    }
  ],
  "usageHints": {
    "requiresContext": false
  }
}