{
  "id": "1264420",
  "writtenForm": {
    "kanji": "言語",
    "containedKanji": [
      "言",
      "語"
    ]
  },
  "reading": {
    "primary": "げんご",
    "alternatives": [
      "ごんご",
      "げんきょ"
    ]
  },
  "frequency": {
    "kanjiRank": 5555,
    "kanaRank": 135757
  },
  "progression": {
    "kklcStep": 222
  },
  "senses": [
    {
      "pos": [
        "n"
      ],
      "misc": {
        "isAbbreviation": false,
        "isSuffix": false,
        "isPrefix": false,
        "isArchaic": false,
        "isRare": false,
        "rawTags": []
      },
      "glosses": [
        "language"
      ],
      "related": {
        "compounds": []
      }
    }
  ],
  "usageHints": {
    "requiresContext": true
  }
}