{
  "id": "1265000",
  "writtenForm": {
    "kanji": "個別",
    "containedKanji": [
      "個",
      "別"
    ]
  },
  "reading": {
    "primary": "こべつ",
    "alternatives": []
  },
  "frequency": {
    "kanjiRank": 8083,
    "kanaRank": 246539
  },
  "progression": {
    "kklcStep": 262
  },
  "senses": [
    {
      "pos": [
        "adj-no"
      ],
      "misc": {
        "isAbbreviation": false,
        "isSuffix": false,
        "isPrefix": false,
        "isArchaic": false,
        "isRare": false,
        "rawTags": []
      },
      "glosses": [
        "individual",
        "separate",
        "personal",
        "case-by-case"
      ],
      "related": {
        "compounds": []
      }
    }
  ],
  "usageHints": {
    "requiresContext": false
  }
}