{
  "id": "1268060",
  "writtenForm": {
    "kanji": "五",
    "containedKanji": [
      "五"
    ]
  },
  "reading": {
    "primary": "ご",
    "alternatives": [
      "いつ",
      "い"
    ]
  },
  "frequency": {
    "kanjiRank": 1316
  },
  "progression": {
    "kklcStep": 7
  },
  "senses": [
    {
      "pos": [
        "num"
      ],
      "misc": {
        "isAbbreviation": false,
        "isSuffix": false,
        "isPrefix": false,
        "isArchaic": false,
        "isRare": false,
        "rawTags": []
      },
      "glosses": [
        "five",
        "5"
      ],
      "related": {
        "compounds": []
      }
    }
  ],
  "usageHints": {
    "requiresContext": true
  }
}