{
  "id": "1286930",
  "writtenForm": {
    "kanji": "国内",
    "containedKanji": [
      "国",
      "内"
    ]
  },
  "reading": {
    "primary": "こくない",
    "alternatives": []
  },
  "frequency": {
    "kanjiRank": 4818
  },
  "progression": {
    "kklcStep": 215
  },
  "senses": [
    {
      "pos": [
        "adj-no",
        "n"
      ],
      "misc": {
        "isAbbreviation": false,
        "isSuffix": false,
        "isPrefix": false,
        "isArchaic": false,
        "isRare": false,
        "rawTags": []
      },
      "glosses": [
        "within the country",
        "inside the county",
        "domestic",
        "home",
        "internal"
      ],
      "related": {
        "compounds": [
          "国外"
        ]
      }
    }
  ],
  "usageHints": {
    "requiresContext": false
  }
}