{
  "id": "1292960",
  "kanji": "再生",
  "readings": [
    "さいせい"
  ],
  "meanings": [
    "restoration to life",
    "coming to life again",
    "resuscitation",
    "regeneration",
    "reformation",
    "rehabilitation",
    "recycling",
    "reclamation",
    "recovery",
    "playback",
    "regeneration (of video or sound)",
    "views (of an online video)",
    "regeneration (of lost or damaged tissue)",
    "regrowth",
    "rebirth",
    "reincarnation",
    "recall (memory)",
    "retrieval"
  ],
  "frequency": 3539,
  "hiraganaFrequency": 143894,
  "containedKanji": [
    "再",
    "生"
  ],
  "pos": [
    "n",
    "vs",
    "vt",
    "vi",
    "n",
    "vs",
    "vi",
    "n",
    "vs",
    "vt",
    "n",
    "vs",
    "vt",
    "n",
    "vs",
    "vt",
    "vi",
    "n",
    "vs",
    "vt",
    "n",
    "vs",
    "vt",
    "vi"
  ]
}