{
  "id": "1306280",
  "writtenForm": {
    "kanji": "使用人",
    "containedKanji": [
      "使",
      "用",
      "人"
    ]
  },
  "reading": {
    "primary": "しようにん",
    "alternatives": []
  },
  "frequency": {
    "kanjiRank": 8149
  },
  "progression": {
    "kklcStep": 887
  },
  "senses": [
    {
      "pos": [
        "n"
      ],
      "misc": {
        "isAbbreviation": false,
        "isSuffix": false,
        "isPrefix": false,
        "isArchaic": false,
        "isRare": false,
        "rawTags": []
      },
      "glosses": [
        "employee",
        "servant"
      ],
      "related": {
        "compounds": []
      }
    }
  ],
  "usageHints": {
    "requiresContext": false
  }
}