{
  "id": "1321900",
  "writtenForm": {
    "kanji": "写真",
    "containedKanji": [
      "写",
      "真"
    ]
  },
  "reading": {
    "primary": "しゃしん",
    "alternatives": []
  },
  "frequency": {
    "kanjiRank": 988,
    "kanaRank": 97090
  },
  "progression": {
    "kklcStep": 859
  },
  "senses": [
    {
      "pos": [
        "n"
      ],
      "misc": {
        "isAbbreviation": false,
        "isSuffix": false,
        "isPrefix": false,
        "isArchaic": false,
        "isRare": false,
        "rawTags": []
      },
      "glosses": [
        "photograph",
        "photo",
        "picture",
        "photography"
      ],
      "related": {
        "compounds": []
      }
    },
    {
      "pos": [
        "n"
      ],
      "misc": {
        "isAbbreviation": true,
        "isSuffix": false,
        "isPrefix": false,
        "isArchaic": false,
        "isRare": false,
        "rawTags": [
          "obs",
          "abbr"
        ]
      },
      "glosses": [
        "moving picture",
        "movie"
      ],
      "related": {
        "compounds": [
          "活動写真"
        ]
      }
    }
  ],
  "usageHints": {
    "requiresContext": false
  }
}