{
  "id": "1359940",
  "writtenForm": {
    "kanji": "唇",
    "containedKanji": [
      "唇"
    ]
  },
  "reading": {
    "primary": "くちびる",
    "alternatives": []
  },
  "frequency": {
    "kanjiRank": 1327,
    "kanaRank": 15698
  },
  "progression": {
    "kklcStep": 1847
  },
  "senses": [
    {
      "pos": [
        "n"
      ],
      "misc": {
        "isAbbreviation": false,
        "isSuffix": false,
        "isPrefix": false,
        "isArchaic": false,
        "isRare": false,
        "rawTags": []
      },
      "glosses": [
        "lip",
        "lips"
      ],
      "related": {
        "compounds": []
      }
    }
  ],
  "usageHints": {
    "requiresContext": false
  }
}