{
  "id": "1361960",
  "writtenForm": {
    "kanji": "新人",
    "containedKanji": [
      "新",
      "人"
    ]
  },
  "reading": {
    "primary": "しんじん",
    "alternatives": []
  },
  "frequency": {
    "kanjiRank": 4445,
    "kanaRank": 288063
  },
  "progression": {
    "kklcStep": 275
  },
  "senses": [
    {
      "pos": [
        "n"
      ],
      "misc": {
        "isAbbreviation": false,
        "isSuffix": false,
        "isPrefix": false,
        "isArchaic": false,
        "isRare": false,
        "rawTags": []
      },
      "glosses": [
        "newcomer",
        "new figure",
        "new member",
        "recruit",
        "rookie",
        "new talent",
        "new star"
      ],
      "related": {
        "compounds": []
      }
    },
    {
      "pos": [
        "n"
      ],
      "misc": {
        "isAbbreviation": false,
        "isSuffix": false,
        "isPrefix": false,
        "isArchaic": false,
        "isRare": false,
        "rawTags": []
      },
      "glosses": [
        "modern humans (from Cro-Magnon man onwards)",
        "Homo sapiens"
      ],
      "related": {
        "compounds": []
      }
    }
  ],
  "usageHints": {
    "requiresContext": false
  }
}