{
  "id": "1378520",
  "kanji": "生きる",
  "readings": [
    "いきる"
  ],
  "meanings": [
    "to live",
    "to exist",
    "to make a living",
    "to subsist",
    "to be in effect",
    "to be in use",
    "to function",
    "to come to life",
    "to be enlivened",
    "to be safe (in baseball, go, etc.)"
  ],
  "frequency": 245,
  "hiraganaFrequency": 23587,
  "containedKanji": [
    "生"
  ],
  "pos": [
    "v1",
    "vi",
    "v1",
    "vi",
    "v1",
    "vi",
    "v1",
    "vi",
    "v1",
    "vi"
  ]
}