{
  "id": "1378860",
  "writtenForm": {
    "kanji": "生活",
    "containedKanji": [
      "生",
      "活"
    ]
  },
  "reading": {
    "primary": "せいかつ",
    "alternatives": []
  },
  "frequency": {
    "kanjiRank": 409,
    "kanaRank": 90878
  },
  "progression": {
    "kklcStep": 54
  },
  "senses": [
    {
      "pos": [
        "n",
        "vs",
        "vi"
      ],
      "misc": {
        "isAbbreviation": false,
        "isSuffix": false,
        "isPrefix": false,
        "isArchaic": false,
        "isRare": false,
        "rawTags": []
      },
      "glosses": [
        "life",
        "living"
      ],
      "related": {
        "compounds": []
      }
    },
    {
      "pos": [
        "n"
      ],
      "misc": {
        "isAbbreviation": false,
        "isSuffix": false,
        "isPrefix": false,
        "isArchaic": false,
        "isRare": false,
        "rawTags": []
      },
      "glosses": [
        "livelihood",
        "(one's) living"
      ],
      "related": {
        "compounds": []
      }
    }
  ],
  "usageHints": {
    "requiresContext": false
  }
}