{
  "id": "1379750",
  "kanji": "盛ん",
  "readings": [
    "さかん"
  ],
  "meanings": [
    "prosperous",
    "flourishing",
    "thriving",
    "successful",
    "popular",
    "widespread",
    "active",
    "lively",
    "energetic",
    "vigorous",
    "brisk",
    "strong",
    "enthusiastic",
    "eager",
    "hearty",
    "frequent",
    "repeated"
  ],
  "frequency": 7543,
  "hiraganaFrequency": 20398,
  "containedKanji": [
    "盛"
  ],
  "pos": [
    "adj-na",
    "adj-na",
    "adj-na",
    "adj-na"
  ]
}