{
  "id": "1400850",
  "writtenForm": {
    "kanji": "相応しい",
    "containedKanji": [
      "相",
      "応"
    ]
  },
  "reading": {
    "primary": "ふさわしい",
    "alternatives": []
  },
  "frequency": {
    "kanjiRank": 4113,
    "kanaRank": 2767
  },
  "progression": {
    "kklcStep": 850
  },
  "senses": [
    {
      "pos": [
        "adj-i"
      ],
      "misc": {
        "isAbbreviation": false,
        "isSuffix": false,
        "isPrefix": false,
        "isArchaic": false,
        "isRare": false,
        "rawTags": [
          "uk"
        ]
      },
      "glosses": [
        "appropriate",
        "adequate",
        "suitable",
        "fitting",
        "worthy"
      ],
      "related": {
        "compounds": []
      }
    }
  ],
  "usageHints": {
    "requiresContext": false
  }
}