{
  "id": "1410290",
  "writtenForm": {
    "kanji": "対立",
    "containedKanji": [
      "対",
      "立"
    ]
  },
  "reading": {
    "primary": "たいりつ",
    "alternatives": []
  },
  "frequency": {
    "kanjiRank": 5433,
    "kanaRank": 233080
  },
  "progression": {
    "kklcStep": 650
  },
  "senses": [
    {
      "pos": [
        "n",
        "vs",
        "vi",
        "adj-no"
      ],
      "misc": {
        "isAbbreviation": false,
        "isSuffix": false,
        "isPrefix": false,
        "isArchaic": false,
        "isRare": false,
        "rawTags": []
      },
      "glosses": [
        "confrontation",
        "opposition",
        "antagonism"
      ],
      "related": {
        "compounds": []
      }
    }
  ],
  "usageHints": {
    "requiresContext": false
  }
}