{
  "id": "1421900",
  "writtenForm": {
    "kanji": "致す",
    "containedKanji": [
      "致"
    ]
  },
  "reading": {
    "primary": "いたす",
    "alternatives": []
  },
  "frequency": {
    "kanjiRank": 3549,
    "kanaRank": 949
  },
  "progression": {
    "kklcStep": 251
  },
  "senses": [
    {
      "pos": [
        "v5s",
        "vt"
      ],
      "misc": {
        "isAbbreviation": false,
        "isSuffix": false,
        "isPrefix": false,
        "isArchaic": false,
        "isRare": false,
        "rawTags": [
          "hum",
          "uk"
        ]
      },
      "glosses": [
        "to do"
      ],
      "related": {
        "compounds": []
      }
    }
  ],
  "usageHints": {
    "requiresContext": false
  }
}