{
  "id": "1442730",
  "writtenForm": {
    "kanji": "田",
    "containedKanji": [
      "田"
    ]
  },
  "reading": {
    "primary": "た",
    "alternatives": []
  },
  "frequency": {
    "kanjiRank": 2236
  },
  "progression": {
    "kklcStep": 20
  },
  "senses": [
    {
      "pos": [
        "n"
      ],
      "misc": {
        "isAbbreviation": false,
        "isSuffix": false,
        "isPrefix": false,
        "isArchaic": false,
        "isRare": false,
        "rawTags": []
      },
      "glosses": [
        "rice field"
      ],
      "related": {
        "compounds": []
      }
    }
  ],
  "usageHints": {
    "requiresContext": false
  }
}