{
  "id": "1473230",
  "writtenForm": {
    "kanji": "倍",
    "containedKanji": [
      "倍"
    ]
  },
  "reading": {
    "primary": "ばい",
    "alternatives": []
  },
  "frequency": {
    "kanjiRank": 2489,
    "kanaRank": 22344
  },
  "progression": {
    "kklcStep": 69
  },
  "senses": [
    {
      "pos": [
        "n",
        "adj-no"
      ],
      "misc": {
        "isAbbreviation": false,
        "isSuffix": false,
        "isPrefix": false,
        "isArchaic": false,
        "isRare": false,
        "rawTags": []
      },
      "glosses": [
        "double",
        "twice (as much)"
      ],
      "related": {
        "compounds": []
      }
    },
    {
      "pos": [
        "ctr"
      ],
      "misc": {
        "isAbbreviation": false,
        "isSuffix": false,
        "isPrefix": false,
        "isArchaic": false,
        "isRare": false,
        "rawTags": []
      },
      "glosses": [
        "times (as much)",
        "-fold"
      ],
      "related": {
        "compounds": []
      }
    },
    {
      "pos": [
        "ctr"
      ],
      "misc": {
        "isAbbreviation": false,
        "isSuffix": false,
        "isPrefix": false,
        "isArchaic": false,
        "isRare": false,
        "rawTags": []
      },
      "glosses": [
        "1-nth",
        "1 to n",
        "1 in n"
      ],
      "related": {
        "compounds": []
      }
    }
  ],
  "usageHints": {
    "requiresContext": false
  }
}