{
  "id": "1474900",
  "writtenForm": {
    "kanji": "白",
    "containedKanji": [
      "白"
    ]
  },
  "reading": {
    "primary": "しろ",
    "alternatives": []
  },
  "frequency": {
    "kanjiRank": 1508,
    "kanaRank": 196937
  },
  "progression": {
    "kklcStep": 76
  },
  "senses": [
    {
      "pos": [
        "n",
        "adj-no"
      ],
      "misc": {
        "isAbbreviation": false,
        "isSuffix": false,
        "isPrefix": false,
        "isArchaic": false,
        "isRare": false,
        "rawTags": []
      },
      "glosses": [
        "white"
      ],
      "related": {
        "compounds": []
      }
    },
    {
      "pos": [
        "n"
      ],
      "misc": {
        "isAbbreviation": false,
        "isSuffix": false,
        "isPrefix": false,
        "isArchaic": false,
        "isRare": false,
        "rawTags": []
      },
      "glosses": [
        "innocence",
        "innocent person"
      ],
      "related": {
        "compounds": []
      }
    },
    {
      "pos": [
        "n"
      ],
      "misc": {
        "isAbbreviation": false,
        "isSuffix": false,
        "isPrefix": false,
        "isArchaic": false,
        "isRare": false,
        "rawTags": []
      },
      "glosses": [
        "blank space"
      ],
      "related": {
        "compounds": []
      }
    },
    {
      "pos": [
        "n"
      ],
      "misc": {
        "isAbbreviation": false,
        "isSuffix": false,
        "isPrefix": false,
        "isArchaic": false,
        "isRare": false,
        "rawTags": []
      },
      "glosses": [
        "white stone"
      ],
      "related": {
        "compounds": []
      }
    },
    {
      "pos": [
        "n"
      ],
      "misc": {
        "isAbbreviation": false,
        "isSuffix": false,
        "isPrefix": false,
        "isArchaic": false,
        "isRare": false,
        "rawTags": []
      },
      "glosses": [
        "white dragon tile"
      ],
      "related": {
        "compounds": [
          "白"
        ]
      }
    },
    {
      "pos": [
        "n"
      ],
      "misc": {
        "isAbbreviation": false,
        "isSuffix": false,
        "isPrefix": false,
        "isArchaic": false,
        "isRare": false,
        "rawTags": []
      },
      "glosses": [
        "skewered grilled pig intestine"
      ],
      "related": {
        "compounds": []
      }
    }
  ],
  "usageHints": {
    "requiresContext": false
  }
}