{
  "id": "1476520",
  "writtenForm": {
    "kanji": "畑",
    "containedKanji": [
      "畑"
    ]
  },
  "reading": {
    "primary": "はたけ",
    "alternatives": [
      "はた"
    ]
  },
  "frequency": {
    "kanjiRank": 3814,
    "kanaRank": 80459
  },
  "progression": {
    "kklcStep": 129
  },
  "senses": [
    {
      "pos": [
        "n"
      ],
      "misc": {
        "isAbbreviation": false,
        "isSuffix": false,
        "isPrefix": false,
        "isArchaic": false,
        "isRare": false,
        "rawTags": []
      },
      "glosses": [
        "field (for growing wheat, fruit, vegetables, etc.)",
        "cultivated land",
        "vegetable plot",
        "kitchen garden",
        "plantation"
      ],
      "related": {
        "compounds": []
      }
    },
    {
      "pos": [
        "n",
        "n-suf"
      ],
      "misc": {
        "isAbbreviation": false,
        "isSuffix": false,
        "isPrefix": false,
        "isArchaic": false,
        "isRare": false,
        "rawTags": []
      },
      "glosses": [
        "field (of specialization)",
        "sphere",
        "area",
        "line"
      ],
      "related": {
        "compounds": []
      }
    },
    {
      "pos": [
        "n"
      ],
      "misc": {
        "isAbbreviation": false,
        "isSuffix": false,
        "isPrefix": false,
        "isArchaic": false,
        "isRare": false,
        "rawTags": [
          "col"
        ]
      },
      "glosses": [
        "womb",
        "birth",
        "birthplace"
      ],
      "related": {
        "compounds": []
      }
    }
  ],
  "usageHints": {
    "requiresContext": true
  }
}