{
  "id": "1477680",
  "writtenForm": {
    "kanji": "発達",
    "containedKanji": [
      "発",
      "達"
    ]
  },
  "reading": {
    "primary": "はったつ",
    "alternatives": []
  },
  "frequency": {
    "kanjiRank": 6730,
    "kanaRank": 204145
  },
  "progression": {
    "kklcStep": 1475
  },
  "senses": [
    {
      "pos": [
        "n",
        "vs",
        "vi"
      ],
      "misc": {
        "isAbbreviation": false,
        "isSuffix": false,
        "isPrefix": false,
        "isArchaic": false,
        "isRare": false,
        "rawTags": []
      },
      "glosses": [
        "development",
        "growth"
      ],
      "related": {
        "compounds": []
      }
    }
  ],
  "usageHints": {
    "requiresContext": false
  }
}