{
  "id": "1486350",
  "writtenForm": {
    "kanji": "美",
    "containedKanji": [
      "美"
    ]
  },
  "reading": {
    "primary": "び",
    "alternatives": []
  },
  "frequency": {
    "kanjiRank": 3409
  },
  "progression": {
    "kklcStep": 497
  },
  "senses": [
    {
      "pos": [
        "n",
        "n-suf"
      ],
      "misc": {
        "isAbbreviation": false,
        "isSuffix": false,
        "isPrefix": false,
        "isArchaic": false,
        "isRare": false,
        "rawTags": []
      },
      "glosses": [
        "beauty"
      ],
      "related": {
        "compounds": []
      }
    }
  ],
  "usageHints": {
    "requiresContext": false
  }
}