{
  "id": "1498100",
  "writtenForm": {
    "kanji": "負傷",
    "containedKanji": [
      "負",
      "傷"
    ]
  },
  "reading": {
    "primary": "ふしょう",
    "alternatives": []
  },
  "frequency": {
    "kanjiRank": 6677,
    "kanaRank": 217006
  },
  "progression": {
    "kklcStep": 1307
  },
  "senses": [
    {
      "pos": [
        "n",
        "vs",
        "vt",
        "vi"
      ],
      "misc": {
        "isAbbreviation": false,
        "isSuffix": false,
        "isPrefix": false,
        "isArchaic": false,
        "isRare": false,
        "rawTags": []
      },
      "glosses": [
        "injury",
        "wound"
      ],
      "related": {
        "compounds": []
      }
    }
  ],
  "usageHints": {
    "requiresContext": false
  }
}