{
  "id": "1541290",
  "writtenForm": {
    "kanji": "有効",
    "containedKanji": [
      "有",
      "効"
    ]
  },
  "reading": {
    "primary": "ゆうこう",
    "alternatives": []
  },
  "frequency": {
    "kanjiRank": 4263,
    "kanaRank": 122144
  },
  "progression": {
    "kklcStep": 1413
  },
  "senses": [
    {
      "pos": [
        "adj-na",
        "n"
      ],
      "misc": {
        "isAbbreviation": false,
        "isSuffix": false,
        "isPrefix": false,
        "isArchaic": false,
        "isRare": false,
        "rawTags": []
      },
      "glosses": [
        "valid",
        "effective"
      ],
      "related": {
        "compounds": []
      }
    },
    {
      "pos": [
        "n"
      ],
      "misc": {
        "isAbbreviation": false,
        "isSuffix": false,
        "isPrefix": false,
        "isArchaic": false,
        "isRare": false,
        "rawTags": []
      },
      "glosses": [
        "yuko (judo)"
      ],
      "related": {
        "compounds": []
      }
    }
  ],
  "usageHints": {
    "requiresContext": false
  }
}