{
  "id": "1548590",
  "writtenForm": {
    "kanji": "落ち着き",
    "containedKanji": [
      "落",
      "着"
    ]
  },
  "reading": {
    "primary": "おちつき",
    "alternatives": []
  },
  "frequency": {
    "kanjiRank": 5293,
    "kanaRank": 54899
  },
  "progression": {
    "kklcStep": 938
  },
  "senses": [
    {
      "pos": [
        "n"
      ],
      "misc": {
        "isAbbreviation": false,
        "isSuffix": false,
        "isPrefix": false,
        "isArchaic": false,
        "isRare": false,
        "rawTags": []
      },
      "glosses": [
        "calmness",
        "composure",
        "presence of mind"
      ],
      "related": {
        "compounds": []
      }
    },
    {
      "pos": [
        "n"
      ],
      "misc": {
        "isAbbreviation": false,
        "isSuffix": false,
        "isPrefix": false,
        "isArchaic": false,
        "isRare": false,
        "rawTags": []
      },
      "glosses": [
        "stability",
        "steadiness"
      ],
      "related": {
        "compounds": []
      }
    }
  ],
  "usageHints": {
    "requiresContext": false
  }
}