{
  "id": "1589840",
  "writtenForm": {
    "kanji": "係",
    "containedKanji": [
      "係"
    ]
  },
  "reading": {
    "primary": "かかり",
    "alternatives": []
  },
  "frequency": {
    "kanjiRank": 4166
  },
  "progression": {
    "kklcStep": 1078
  },
  "senses": [
    {
      "pos": [
        "n"
      ],
      "misc": {
        "isAbbreviation": false,
        "isSuffix": false,
        "isPrefix": false,
        "isArchaic": false,
        "isRare": false,
        "rawTags": []
      },
      "glosses": [
        "charge",
        "duty",
        "person in charge",
        "official",
        "clerk"
      ],
      "related": {
        "compounds": [
          "掛かり"
        ]
      }
    },
    {
      "pos": [
        "n"
      ],
      "misc": {
        "isAbbreviation": false,
        "isSuffix": false,
        "isPrefix": false,
        "isArchaic": false,
        "isRare": false,
        "rawTags": []
      },
      "glosses": [
        "connection",
        "linking"
      ],
      "related": {
        "compounds": [
          "係り結び"
        ]
      }
    }
  ],
  "usageHints": {
    "requiresContext": false
  }
}